ARCHITECTURE.txt
CHANGES
DESIGN.txt
LICENSE
MANIFEST.in
README.md
TODO
requirements.txt
setup.cfg
setup.py
tox.ini
bind9_parser/__init__.py
bind9_parser/isc_acl.py
bind9_parser/isc_aml.py
bind9_parser/isc_clause.py
bind9_parser/isc_clause_acl.py
bind9_parser/isc_clause_controls.py
bind9_parser/isc_clause_dlz.py
bind9_parser/isc_clause_dyndb.py
bind9_parser/isc_clause_key.py
bind9_parser/isc_clause_logging.py
bind9_parser/isc_clause_managed_keys.py
bind9_parser/isc_clause_masters.py
bind9_parser/isc_clause_options.py
bind9_parser/isc_clause_server.py
bind9_parser/isc_clause_trusted_keys.py
bind9_parser/isc_clause_view.py
bind9_parser/isc_clause_zone.py
bind9_parser/isc_domain.py
bind9_parser/isc_inet.py
bind9_parser/isc_managed_keys.py
bind9_parser/isc_options.py
bind9_parser/isc_optview.py
bind9_parser/isc_optviewserver.py
bind9_parser/isc_optviewzone.py
bind9_parser/isc_optviewzoneserver.py
bind9_parser/isc_optzone.py
bind9_parser/isc_rr.py
bind9_parser/isc_server.py
bind9_parser/isc_trusted_keys.py
bind9_parser/isc_utils.py
bind9_parser/isc_view.py
bind9_parser/isc_viewzone.py
bind9_parser/isc_zone.py
bind9_parser.egg-info/PKG-INFO
bind9_parser.egg-info/SOURCES.txt
bind9_parser.egg-info/dependency_links.txt
bind9_parser.egg-info/requires.txt
bind9_parser.egg-info/top_level.txt
docs/README
examples/README
examples/exclamation.py
examples/flatten_namedconf.py
examples/isc_boolean.py
examples/named-zytrax.conf
examples/parse_bind9.py
examples/try-me.sh